{
  "_class": "shapePath",
  "booleanOperation": -1,
  "clippingMaskMode": 0,
  "do_objectID": "7A1B9A3B-AF5C-4D2C-A02B-8BB2D0DFD020",
  "edited": true,
  "exportOptions": {
    "_class": "exportOptions",
    "do_objectID": "A991FA3B-E102-4DB0-9CD3-98DA386E75D9",
    "exportFormats": [
    ],
    "includedLayerIds": [
    ],
    "layerOptions": 0,
    "shouldTrim": false
  },
  "frame": {
    "_class": "rect",
    "constrainProportions": false,
    "do_objectID": "043632AF-4758-4244-BCD1-5A8DDC6C1BD0",
    "height": 15.19722436226971,
    "width": 16,
    "x": 1,
    "y": 1
  },
  "hasClippingMask": false,
  "isClosed": true,
  "isFixedToViewport": false,
  "isFlippedHorizontal": false,
  "isFlippedVertical": false,
  "isLocked": false,
  "isVisible": true,
  "layerListExpandedType": 0,
  "name": "Path",
  "nameIsFixed": false,
  "pointRadiusBehaviour": 1,
  "points": [
    {
      "_class": "curvePoint",
      "cornerRadius": 0,
      "curveFrom": "{0.63321768176117033, 0.7896178745503365}",
      "curveMode": 1,
      "curveTo": "{0.63321768176117033, 0.7896178745503365}",
      "hasCurveFrom": false,
      "hasCurveTo": false,
      "point": "{0.63321768176117033, 0.7896178745503365}"
    },
    {
      "_class": "curvePoint",
      "cornerRadius": 0,
      "curveFrom": "{1, 0.7896178745503365}",
      "curveMode": 1,
      "curveTo": "{1, 0.7896178745503365}",
      "hasCurveFrom": false,
      "hasCurveTo": false,
      "point": "{1, 0.7896178745503365}"
    },
    {
      "_class": "curvePoint",
      "cornerRadius": 0,
      "curveFrom": "{1, 0}",
      "curveMode": 1,
      "curveTo": "{1, 0}",
      "hasCurveFrom": false,
      "hasCurveTo": false,
      "point": "{1, 0}"
    },
    {
      "_class": "curvePoint",
      "cornerRadius": 0,
      "curveFrom": "{0, 0}",
      "curveMode": 1,
      "curveTo": "{0, 0}",
      "hasCurveFrom": false,
      "hasCurveTo": false,
      "point": "{0, 0}"
    },
    {
      "_class": "curvePoint",
      "cornerRadius": 0,
      "curveFrom": "{0, 0.78961787455046373}",
      "curveMode": 1,
      "curveTo": "{0, 0.78961787455046373}",
      "hasCurveFrom": false,
      "hasCurveTo": false,
      "point": "{0, 0.78961787455046373}"
    },
    {
      "_class": "curvePoint",
      "cornerRadius": 0,
      "curveFrom": "{0.36678231823882967, 0.7896178745503365}",
      "curveMode": 1,
      "curveTo": "{0.36678231823882967, 0.7896178745503365}",
      "hasCurveFrom": false,
      "hasCurveTo": false,
      "point": "{0.36678231823882967, 0.7896178745503365}"
    },
    {
      "_class": "curvePoint",
      "cornerRadius": 0,
      "curveFrom": "{0.5000000000000604, 1}",
      "curveMode": 1,
      "curveTo": "{0.5000000000000604, 1}",
      "hasCurveFrom": false,
      "hasCurveTo": false,
      "point": "{0.5000000000000604, 1}"
    }
  ],
  "resizingConstraint": 63,
  "resizingType": 0,
  "rotation": 0,
  "shouldBreakMaskChain": false,
  "style": {
    "_class": "style",
    "do_objectID": "33E7725D-F2F3-4A92-AF94-55BF818D8430",
    "endMarkerType": 0,
    "fills": [
      {
        "_class": "fill",
        "color": {
          "_class": "color",
          "alpha": 1,
          "blue": 1,
          "green": 1,
          "red": 1
        },
        "fillType": 0,
        "isEnabled": true,
        "noiseIndex": 0,
        "noiseIntensity": 0,
        "patternFillType": 1,
        "patternTileScale": 1
      }
    ],
    "miterLimit": 10,
    "startMarkerType": 0,
    "windingRule": 0
  }
}