{
  "_class": "text",
  "attributedString": {
    "_class": "attributedString",
    "attributes": [
      {
        "_class": "stringAttribute",
        "attributes": {
          "MSAttributedStringColorAttribute": {
            "_class": "color",
            "alpha": 1,
            "blue": 0.2,
            "green": 0.2,
            "red": 0.2
          },
          "MSAttributedStringFontAttribute": {
            "_class": "fontDescriptor",
            "attributes": {
              "name": "PingFangSC-Regular",
              "size": 18
            }
          },
          "kerning": 0,
          "paragraphStyle": {
            "_class": "paragraphStyle",
            "alignment": 3,
            "allowsDefaultTighteningForTruncation": 0,
            "maximumLineHeight": 34,
            "minimumLineHeight": 34
          }
        },
        "length": 105,
        "location": 0
      }
    ],
    "string": "中国一直有“人养玉，玉养人”的说法，认为佩戴玉器制品可以蓄元气、养精神，并起到一定的养生保健效果。玉镯由于戴在腕上，而人的手腕背侧又有“养老穴”，所以长期佩戴和田玉手镯，还能起到良性按摩的作用，真可谓一举两得。"
  },
  "automaticallyDrawOnUnderlyingPath": false,
  "booleanOperation": 0,
  "clippingMaskMode": 0,
  "do_objectID": "593A7FAF-E450-4622-85DA-E84DC4A45AB5",
  "dontSynchroniseWithSymbol": false,
  "exportOptions": {
    "_class": "exportOptions",
    "do_objectID": "8618F90A-200F-489B-B988-4BC73D3DD9F6",
    "exportFormats": [
    ],
    "includedLayerIds": [
    ],
    "layerOptions": 0,
    "shouldTrim": false
  },
  "frame": {
    "_class": "rect",
    "constrainProportions": false,
    "do_objectID": "EFA95B65-92D7-4E1F-AF89-750CD77D5E8B",
    "height": 204,
    "width": 331,
    "x": 22,
    "y": 335
  },
  "glyphBounds": "{{0, 7}, {331, 189}}",
  "hasClippingMask": false,
  "isFixedToViewport": false,
  "isFlippedHorizontal": false,
  "isFlippedVertical": false,
  "isLocked": false,
  "isVisible": true,
  "layerListExpandedType": 0,
  "lineSpacingBehaviour": 2,
  "name": "中国一直有“人养玉，玉养人”的说法，认为",
  "nameIsFixed": false,
  "resizingConstraint": 63,
  "resizingType": 0,
  "rotation": 0,
  "shouldBreakMaskChain": false,
  "style": {
    "_class": "style",
    "blur": {
      "_class": "blur",
      "center": "{0.5, 0.5}",
      "do_objectID": "F0C6CCE5-B90E-4784-9FCD-B1FB38DE7F78",
      "isEnabled": false,
      "motionAngle": 0,
      "radius": 5,
      "saturation": 1,
      "type": 0
    },
    "do_objectID": "AB9411CB-D6EF-4D8A-97DA-FF093A4A2300",
    "endMarkerType": 0,
    "miterLimit": 10,
    "startMarkerType": 0,
    "textStyle": {
      "_class": "textStyle",
      "do_objectID": "0C9F7791-B176-45D2-A586-13C1017AF3CF",
      "encodedAttributes": {
        "MSAttributedStringColorAttribute": {
          "_class": "color",
          "alpha": 1,
          "blue": 0.2,
          "green": 0.2,
          "red": 0.2
        },
        "MSAttributedStringFontAttribute": {
          "_class": "fontDescriptor",
          "attributes": {
            "name": "PingFangSC-Regular",
            "size": 18
          }
        },
        "kerning": 0,
        "paragraphStyle": {
          "_class": "paragraphStyle",
          "alignment": 3,
          "allowsDefaultTighteningForTruncation": 0,
          "maximumLineHeight": 34,
          "minimumLineHeight": 34
        }
      },
      "verticalAlignment": 0
    },
    "windingRule": 1
  },
  "textBehaviour": 1
}