{
  "_class": "bitmap",
  "booleanOperation": -1,
  "clippingMask": "{{0, 0}, {1, 1}}",
  "clippingMaskMode": 0,
  "do_objectID": "37A55D81-A1A7-4218-8612-4D63071780DE",
  "exportOptions": {
    "_class": "exportOptions",
    "exportFormats": [
    ],
    "includedLayerIds": [
    ],
    "layerOptions": 0,
    "shouldTrim": false
  },
  "fillReplacesImage": false,
  "frame": {
    "_class": "rect",
    "constrainProportions": true,
    "height": 345,
    "width": 345,
    "x": 15,
    "y": 933
  },
  "hasClippingMask": false,
  "image": {
    "_class": "MSJSONFileReference",
    "_ref": "images/b5026ea79ad9e937f6840d7b2d854fda41c12767.png",
    "_ref_class": "MSImageData"
  },
  "intendedDPI": 72,
  "isFixedToViewport": false,
  "isFlippedHorizontal": false,
  "isFlippedVertical": false,
  "isLocked": false,
  "isVisible": true,
  "layerListExpandedType": 0,
  "name": "941553650464_.pic_hd",
  "nameIsFixed": false,
  "resizingConstraint": 63,
  "resizingType": 0,
  "rotation": 0,
  "shouldBreakMaskChain": false,
  "style": {
    "_class": "style",
    "endMarkerType": 0,
    "miterLimit": 10,
    "startMarkerType": 0,
    "windingRule": 1
  }
}