{
  "_class": "shapePath",
  "booleanOperation": 0,
  "clippingMaskMode": 0,
  "do_objectID": "2137DC84-5909-4E52-A48F-2D9CF27BD625",
  "edited": true,
  "exportOptions": {
    "_class": "exportOptions",
    "do_objectID": "883F62DF-2E4D-4AF1-865D-DE7255E6B70A",
    "exportFormats": [
    ],
    "includedLayerIds": [
    ],
    "layerOptions": 0,
    "shouldTrim": false
  },
  "frame": {
    "_class": "rect",
    "constrainProportions": true,
    "do_objectID": "DB6CA715-1614-42A0-BB8C-11C6AB934570",
    "height": 17,
    "width": 17,
    "x": 0.1446280991735591,
    "y": 0
  },
  "hasClippingMask": false,
  "isClosed": false,
  "isFixedToViewport": false,
  "isFlippedHorizontal": false,
  "isFlippedVertical": false,
  "isLocked": false,
  "isVisible": true,
  "layerListExpandedType": 0,
  "name": "Path",
  "nameIsFixed": false,
  "originalObjectID": "26E3F445-75AC-4B6D-BA29-2EF8C3F244CC",
  "pointRadiusBehaviour": 0,
  "points": [
    {
      "_class": "curvePoint",
      "cornerRadius": 0,
      "curveFrom": "{0.77609999999999668, 0}",
      "curveMode": 4,
      "curveTo": "{0.5, 0}",
      "hasCurveFrom": true,
      "hasCurveTo": false,
      "point": "{0.5, 0}"
    },
    {
      "_class": "curvePoint",
      "cornerRadius": 0,
      "curveFrom": "{1, 0.7760999999999999}",
      "curveMode": 2,
      "curveTo": "{1, 0.22379999999999994}",
      "hasCurveFrom": true,
      "hasCurveTo": true,
      "point": "{1, 0.5}"
    },
    {
      "_class": "curvePoint",
      "cornerRadius": 0,
      "curveFrom": "{0.2238999999999976, 1}",
      "curveMode": 2,
      "curveTo": "{0.77609999999999668, 1}",
      "hasCurveFrom": true,
      "hasCurveTo": true,
      "point": "{0.5, 1}"
    },
    {
      "_class": "curvePoint",
      "cornerRadius": 0,
      "curveFrom": "{0, 0.22379999999999994}",
      "curveMode": 2,
      "curveTo": "{0, 0.7760999999999999}",
      "hasCurveFrom": true,
      "hasCurveTo": true,
      "point": "{0, 0.5}"
    },
    {
      "_class": "curvePoint",
      "cornerRadius": 0,
      "curveFrom": "{0.5, 0}",
      "curveMode": 4,
      "curveTo": "{0.2238999999999976, 0}",
      "hasCurveFrom": false,
      "hasCurveTo": true,
      "point": "{0.5, 0}"
    }
  ],
  "resizingConstraint": 63,
  "resizingType": 0,
  "rotation": 0,
  "shouldBreakMaskChain": false,
  "style": {
    "_class": "style",
    "blur": {
      "_class": "blur",
      "center": "{0.5, 0.5}",
      "do_objectID": "E4BF7AE2-0BD6-42BA-ABEC-70A5C4F0D2DA",
      "isEnabled": false,
      "motionAngle": 0,
      "radius": 5,
      "saturation": 1,
      "type": 0
    },
    "borders": [
      {
        "_class": "border",
        "color": {
          "_class": "color",
          "alpha": 1,
          "blue": 0,
          "green": 0,
          "red": 0
        },
        "fillType": 0,
        "isEnabled": true,
        "position": 1,
        "thickness": 2
      }
    ],
    "do_objectID": "0703A2C7-81E6-42E2-8EE7-453A9A48D058",
    "endMarkerType": 0,
    "miterLimit": 10,
    "startMarkerType": 0,
    "windingRule": 1
  }
}