{
  "_class": "shapePath",
  "booleanOperation": -1,
  "clippingMaskMode": 0,
  "do_objectID": "462FEE23-183E-4594-89B0-DE483F964D3A",
  "edited": true,
  "exportOptions": {
    "_class": "exportOptions",
    "exportFormats": [
    ],
    "includedLayerIds": [
    ],
    "layerOptions": 0,
    "shouldTrim": false
  },
  "frame": {
    "_class": "rect",
    "constrainProportions": false,
    "height": 7.00130147474868,
    "width": 7.361604021201902,
    "x": 2.148961141749629,
    "y": 2.259551461905676
  },
  "hasClippingMask": false,
  "isClosed": true,
  "isFixedToViewport": false,
  "isFlippedHorizontal": false,
  "isFlippedVertical": false,
  "isLocked": false,
  "isVisible": true,
  "layerListExpandedType": 0,
  "name": "Path",
  "nameIsFixed": false,
  "pointRadiusBehaviour": 1,
  "points": [
    {
      "_class": "curvePoint",
      "cornerRadius": 0,
      "curveFrom": "{0.50000000000000078, 0.82917960675006241}",
      "curveMode": 1,
      "curveTo": "{0.50000000000000078, 0.82917960675006241}",
      "hasCurveFrom": false,
      "hasCurveTo": false,
      "point": "{0.50000000000000078, 0.82917960675006241}"
    },
    {
      "_class": "curvePoint",
      "cornerRadius": 0,
      "curveFrom": "{0.80901699437494912, 1}",
      "curveMode": 1,
      "curveTo": "{0.80901699437494912, 1}",
      "hasCurveFrom": false,
      "hasCurveTo": false,
      "point": "{0.80901699437494912, 1}"
    },
    {
      "_class": "curvePoint",
      "cornerRadius": 0,
      "curveFrom": "{0.75000000000000089, 0.6381966011250102}",
      "curveMode": 1,
      "curveTo": "{0.75000000000000089, 0.6381966011250102}",
      "hasCurveFrom": false,
      "hasCurveTo": false,
      "point": "{0.75000000000000089, 0.6381966011250102}"
    },
    {
      "_class": "curvePoint",
      "cornerRadius": 0,
      "curveFrom": "{1, 0.38196601125010582}",
      "curveMode": 1,
      "curveTo": "{1, 0.38196601125010582}",
      "hasCurveFrom": false,
      "hasCurveTo": false,
      "point": "{1, 0.38196601125010582}"
    },
    {
      "_class": "curvePoint",
      "cornerRadius": 0,
      "curveFrom": "{0.65450849718747428, 0.32917960675006314}",
      "curveMode": 1,
      "curveTo": "{0.65450849718747428, 0.32917960675006314}",
      "hasCurveFrom": false,
      "hasCurveTo": false,
      "point": "{0.65450849718747428, 0.32917960675006314}"
    },
    {
      "_class": "curvePoint",
      "cornerRadius": 0,
      "curveFrom": "{0.50000000000000044, 0}",
      "curveMode": 1,
      "curveTo": "{0.50000000000000044, 0}",
      "hasCurveFrom": false,
      "hasCurveTo": false,
      "point": "{0.50000000000000044, 0}"
    },
    {
      "_class": "curvePoint",
      "cornerRadius": 0,
      "curveFrom": "{0.34549150281252688, 0.32917960675006314}",
      "curveMode": 1,
      "curveTo": "{0.34549150281252688, 0.32917960675006314}",
      "hasCurveFrom": false,
      "hasCurveTo": false,
      "point": "{0.34549150281252688, 0.32917960675006314}"
    },
    {
      "_class": "curvePoint",
      "cornerRadius": 0,
      "curveFrom": "{0, 0.38196601125010532}",
      "curveMode": 1,
      "curveTo": "{0, 0.38196601125010532}",
      "hasCurveFrom": false,
      "hasCurveTo": false,
      "point": "{0, 0.38196601125010532}"
    },
    {
      "_class": "curvePoint",
      "cornerRadius": 0,
      "curveFrom": "{0.25000000000000061, 0.6381966011250102}",
      "curveMode": 1,
      "curveTo": "{0.25000000000000061, 0.6381966011250102}",
      "hasCurveFrom": false,
      "hasCurveTo": false,
      "point": "{0.25000000000000061, 0.6381966011250102}"
    },
    {
      "_class": "curvePoint",
      "cornerRadius": 0,
      "curveFrom": "{0.19098300562505333, 0.999999999999999}",
      "curveMode": 1,
      "curveTo": "{0.19098300562505333, 0.999999999999999}",
      "hasCurveFrom": false,
      "hasCurveTo": false,
      "point": "{0.19098300562505333, 0.999999999999999}"
    }
  ],
  "resizingConstraint": 63,
  "resizingType": 0,
  "rotation": 0,
  "shouldBreakMaskChain": false,
  "style": {
    "_class": "style",
    "endMarkerType": 0,
    "fills": [
      {
        "_class": "fill",
        "color": {
          "_class": "color",
          "alpha": 1,
          "blue": 0.2,
          "green": 0.2,
          "red": 0.2
        },
        "fillType": 0,
        "isEnabled": true,
        "noiseIndex": 0,
        "noiseIntensity": 0,
        "patternFillType": 1,
        "patternTileScale": 1
      }
    ],
    "miterLimit": 10,
    "startMarkerType": 0,
    "windingRule": 0
  }
}