{
  "_class": "shapeGroup",
  "booleanOperation": 0,
  "clippingMaskMode": 0,
  "do_objectID": "4B006B06-BAC6-4B6B-9982-18EBA70E21AA",
  "exportOptions": {
    "_class": "exportOptions",
    "do_objectID": "F4F7BB85-63E6-4200-A84A-09F04E1C4EDF",
    "exportFormats": [
    ],
    "includedLayerIds": [
    ],
    "layerOptions": 0,
    "shouldTrim": false
  },
  "frame": {
    "_class": "rect",
    "constrainProportions": true,
    "do_objectID": "E5177170-A33E-4156-AC4E-53E9C9D65C28",
    "height": 6.5,
    "width": 18.5,
    "x": 0.5,
    "y": 7
  },
  "groupLayout": {
    "_class": "MSImmutableFreeformGroupLayout",
    "do_objectID": "0797805B-BDF5-4323-92FA-2390B777E40E"
  },
  "hasClickThrough": false,
  "hasClippingMask": false,
  "isFixedToViewport": false,
  "isFlippedHorizontal": false,
  "isFlippedVertical": false,
  "isLocked": false,
  "isVisible": true,
  "layerListExpandedType": 0,
  "layers": [
    {
      "class": "shapePath",
      "id": "97224176-3F86-45B2-AD56-E2B238F59910"
    },
    {
      "class": "shapePath",
      "id": "CE41FFFF-FEAD-44A2-A6A6-3650FD0C4A6D"
    },
    {
      "class": "shapePath",
      "id": "9194069B-9F9F-43FA-A70A-7F2C26B17A38"
    }
  ],
  "name": "More",
  "nameIsFixed": true,
  "originalObjectID": "3734F6D5-F1BA-42A4-A2E8-8E3DDCFC494A",
  "resizingConstraint": 63,
  "resizingType": 0,
  "rotation": 0,
  "shouldBreakMaskChain": false,
  "style": {
    "_class": "style",
    "blur": {
      "_class": "blur",
      "center": "{0.5, 0.5}",
      "do_objectID": "5F85CB13-060B-4A10-831B-39A2C865697F",
      "isEnabled": false,
      "motionAngle": 0,
      "radius": 5,
      "saturation": 1,
      "type": 0
    },
    "do_objectID": "8C7A351C-B96D-4F38-8F72-B8C8AC42885C",
    "endMarkerType": 0,
    "fills": [
      {
        "_class": "fill",
        "color": {
          "_class": "color",
          "alpha": 1,
          "blue": 0,
          "green": 0,
          "red": 0
        },
        "fillType": 0,
        "isEnabled": true,
        "noiseIndex": 0,
        "noiseIntensity": 0,
        "patternFillType": 0,
        "patternTileScale": 1
      }
    ],
    "miterLimit": 10,
    "startMarkerType": 0,
    "windingRule": 1
  },
  "windingRule": 1
}